CHANGES.txt
LICENSE.txt
MANIFEST.in
setup.py
docs/index.rst
pysignature/__init__.py
pysignature/exceptions.py
pysignature/signature.py
pysignature/types.py
pysignature.egg-info/PKG-INFO
pysignature.egg-info/SOURCES.txt
pysignature.egg-info/dependency_links.txt
pysignature.egg-info/top_level.txt
pysignature/test/test_signature.py
pysignature/test/test_types.py