Metadata-Version: 1.1
Name: pysignature
Version: 0.0.1
Summary: Minimalistic typechecking of function calls
Home-page: https://github.com/intelimetrica/pysignature
Author: Edgar Cabrera
Author-email: ecabrera@intelimetrica.com
License: UNKNOWN
Platform: UNKNOWN
Classifier: Development Status :: 3 - Alpha
Classifier: License :: OSI Approved :: Apache Software License
Classifier: Programming Language :: Python
